{
  "description": "项目配置文件",
  "packOptions": {
    "ignore": []
  },
  "setting": {
    "urlCheck": false,
    "es6": true,
    "enhance": false,
    "postcss": true,
    "preloadBackgroundData": false,
    "minified": true,
    "newFeature": false,
    "coverView": true,
    "nodeModules": false,
    "autoAudits": false,
    "showShadowRootInWxmlPanel": true,
    "scopeDataCheck": false,
    "uglifyFileName": false,
    "checkInvalidKey": true,
    "checkSiteMap": true,
    "uploadWithSourceMap": true,
    "compileHotReLoad": false,
    "babelSetting": {
      "ignore": [],
      "disablePlugins": [],
      "outputPath": ""
    },
    "bundle": false,
    "useIsolateContext": true,
    "useCompilerModule": false,
    "userConfirmedUseCompilerModuleSwitch": false,
    "useMultiFrameRuntime": true,
    "useApiHook": true,
    "useApiHostProcess": true,
    "enableEngineNative": false,
    "userConfirmedBundleSwitch": false,
    "packNpmManually": false,
    "packNpmRelationList": [],
    "minifyWXSS": true
  },
  "compileType": "miniprogram",
  "libVersion": "2.17.0",
  "appid": "wx1f91d931d0297f26",
  "projectname": "bangumi",
  "debugOptions": {
    "hidedInDevtools": []
  },
  "scripts": {},
  "staticServerOptions": {
    "baseURL": "",
    "servePath": ""
  },
  "isGameTourist": false,
  "simulatorType": "wechat",
  "simulatorPluginLibVersion": {},
  "condition": {
    "search": {
      "list": []
    },
    "conversation": {
      "list": []
    },
    "plugin": {
      "list": []
    },
    "game": {
      "list": []
    },
    "gamePlugin": {
      "list": []
    },
    "miniprogram": {
      "list": [
        {
          "id": -1,
          "name": "pages/newRecomm/newRecomm",
          "pathName": "pages/newRecomm/newRecomm",
          "query": "",
          "scene": null
        },
        {
          "id": -1,
          "name": "pages/newRecomm/newRecomm",
          "pathName": "pages/newRecomm/newRecomm",
          "query": "",
          "scene": null
        },
        {
          "id": -1,
          "name": "pages/time/time",
          "pathName": "pages/time/time",
          "scene": null
        }
      ]
    }
  }
}